{
    "Language & Word Origins": [
        {
            "name": "Lexical Labyrinth: Tracing the Roots of Words",
            "description": "Embark on a fascinating journey through the history of language! This quiz explores the surprising origins of common words, delving into their etymological pathways across cultures and time. Prepare to challenge your knowledge and uncover the hidden stories behind the words we use every day.",
            "questions": [
                {
                    "text": "The word 'salary' originates from a rather unusual source. What Roman practice gave rise to its meaning?",
                    "hint": "Think about how Roman soldiers were paid and what they received.",
                    "option1": "A system of bartering goods and services.",
                    "option2": "A tax levied on landowners.",
                    "option3": "Payment in salt, a valuable commodity.",
                    "option4": "A lottery system for distributing resources.",
                    "solution": "3"
                },
                {
                    "text": "The word 'muscle' has a surprisingly animalistic origin. From what ancient Greek word does it derive?",
                    "hint": "Consider the appearance of a bicep and what it might resemble.",
                    "option1": "Phos (light)",
                    "option2": "Demos (people)",
                    "option3": "Myos (mouse)",
                    "option4": "Chronos (time)",
                    "solution": "1"
                },
                {
                    "text": "The word 'disaster' initially referred to a celestial event. What was its original meaning?",
                    "hint": "It's related to astrology and the movement of stars.",
                    "option1": "A period of great prosperity.",
                    "option2": "A sudden and unexpected gift.",
                    "option3": "An unfavorable alignment of the stars.",
                    "option4": "A new scientific discovery.",
                    "solution": "2"
                },
                {
                    "text": "The word 'clue' has a fascinating connection to the game of bowls. What did 'clew' originally refer to?",
                    "hint": "Think about the tools used in an older version of bowling.",
                    "option1": "A type of scoring system.",
                    "option2": "A specific type of bowling ball.",
                    "option3": "A ball used in bowls.",
                    "option4": "The playing field itself.",
                    "solution": "4"
                },
                {
                    "text": "The word 'calculate' has roots in Latin. What does 'calculus' originally mean?",
                    "hint": "It's related to pebbles and counting.",
                    "option1": "A complex mathematical equation.",
                    "option2": "A type of ancient Roman currency.",
                    "option3": "A small stone used for counting.",
                    "option4": "A system of astronomical measurement.",
                    "solution": "2"
                },
                {
                    "text": "The word 'robot' is relatively modern, but its origin is quite old. From which language and word does it derive?",
                    "hint": "It's connected to forced labor and servitude.",
                    "option1": "German - 'Arbeit' (work)",
                    "option2": "French - 'Automate' (automatic)",
                    "option3": "Czech - 'robota' (forced labor).",
                    "option4": "Greek - 'automatos' (self-moving)",
                    "solution": "4"
                },
                {
                    "text": "The word 'nomad' shares a linguistic ancestor with the word 'name'. What does the Proto-Indo-European root *h1nomn mean?",
                    "hint": "It relates to belonging and being known.",
                    "option1": "To wander aimlessly.",
                    "option2": "To build a permanent structure.",
                    "option3": "To have a name or be known.",
                    "option4": "To possess great wealth.",
                    "solution": "3"
                },
                {
                    "text": "The word 'quarantine' has a dark history linked to the Black Death. What does the Italian word 'quaranta' signify?",
                    "hint": "It's a number related to the duration of isolation.",
                    "option1": "A type of medicinal herb.",
                    "option2": "A specific geographic location.",
                    "option3": "Forty days.",
                    "option4": "A religious ceremony.",
                    "solution": "4"
                }
            ]
        },
        {
            "name": "Echoes of Antiquity: A Word Origin Expedition",
            "description": "Delve into the fascinating histories of words! This quiz explores the surprising origins and transformations of common terms, tracing their journeys across languages and cultures. Prepare to uncover the unexpected stories behind the words we use every day. Let's see how much you know about the echoes of antiquity embedded in our lexicon.",
            "questions": [
                {
                    "text": "The word 'salary' originates from a surprising source. What Roman practice gave rise to this term?",
                    "hint": "Think about how Roman soldiers were compensated.",
                    "option1": "A system of bartering for goods and services.",
                    "option2": "Payment in land grants for military service.",
                    "option3": "A lottery system distributing spoils of war.",
                    "option4": "Payment to soldiers in salt (salarium)",
                    "solution": "4"
                },
                {
                    "text": "The word 'muscle' has a rather evocative etymological root. From which Greek word does it derive, referencing a specific physical characteristic?",
                    "hint": "Consider the appearance of a bicep muscle.",
                    "option1": "Phos (light)",
                    "option2": "Mys (mouse)",
                    "option3": "Kardia (heart)",
                    "option4": "Daktylos (finger)",
                    "solution": "2"
                },
                {
                    "text": "The word 'clue' originally meant something quite different than its current meaning of a hint or indication. What was its initial meaning?",
                    "hint": "It's related to a legal process.",
                    "option1": "A secret passage or hidden doorway.",
                    "option2": "A type of ancient coin used for payment.",
                    "option3": "A formal accusation or indictment in court.",
                    "option4": "A specific type of knot used in sailing.",
                    "solution": "1"
                },
                {
                    "text": "The word 'disaster' comes from the Italian 'disastro'. What does 'disastro' literally translate to?",
                    "hint": "Think about astrological events.",
                    "option1": "A sudden and unexpected windfall.",
                    "option2": "A period of great prosperity and abundance.",
                    "option3": "An unfavorable alignment of the stars.",
                    "option4": "A celebration of a successful harvest.",
                    "solution": "4"
                },
                {
                    "text": "The word 'robot' was popularized by Karel Capek, but where did he draw inspiration for the term?",
                    "hint": "It's a Slavic word with a specific meaning.",
                    "option1": "A Czech folk tale about mechanical servants.",
                    "option2": "A Latin term for automated labor.",
                    "option3": "The Czech word 'robota' meaning forced labor or servitude.",
                    "option4": "An ancient Greek myth about artificial beings.",
                    "solution": "1"
                },
                {
                    "text": "The word 'calculate' has a fascinating connection to the Roman Empire. What did the Latin word 'calculus' originally refer to?",
                    "hint": "Think about what Roman officials used for counting.",
                    "option1": "A type of Roman chariot.",
                    "option2": "A system of Roman roads.",
                    "option3": "Small stones used for counting and abacus calculations.",
                    "option4": "A form of Roman currency.",
                    "solution": "4"
                },
                {
                    "text": "The word 'nomad' derives from a Greek term. What does the Greek word 'nomos' signify, and how does it relate to the meaning of 'nomad'?",
                    "hint": "It's connected to a fundamental aspect of societal organization.",
                    "option1": "A type of ancient Greek pottery.",
                    "option2": "Pasture or grazing land.",
                    "option3": "A system of religious rituals and ceremonies.",
                    "option4": "A form of ancient Greek poetry.",
                    "solution": "1"
                },
                {
                    "text": "The word 'quarantine' has a dark and significant history, originating in response to outbreaks of disease. From what Venetian term does it derive?",
                    "hint": "It refers to a period of isolation.",
                    "option1": "Festivo (festive)",
                    "option2": "Sanato (healed)",
                    "option3": "Quaranta giorni (forty days)",
                    "option4": "Vento forte (strong wind)",
                    "solution": "4"
                }
            ]
        },
        {
            "name": "Chronicles of Nomenclature: A Linguistic Journey",
            "description": "Delve into the fascinating histories of words! This quiz explores the surprising origins and transformations of common terms, revealing how language evolves over time and across cultures. Prepare to uncover the unexpected stories behind the words we use every day.",
            "questions": [
                {
                    "text": "The word 'salary' originates from a rather unusual source. From which Roman practice does it derive?",
                    "hint": "Think about how ancient Romans were sometimes paid.",
                    "option1": "Payment in gold coins minted by Emperor Salvius Julianus.",
                    "option2": "A system of bartering goods and services.",
                    "option3": "Payment in livestock, primarily sheep.",
                    "option4": "Payment in salt, a valuable commodity.",
                    "solution": "4"
                },
                {
                    "text": "The word 'muscle' has a surprisingly visual etymological root. What did the Latin word 'musculus' originally refer to?",
                    "hint": "Consider the appearance of a small mouse.",
                    "option1": "A type of Roman armor.",
                    "option2": "A small mouse.",
                    "option3": "A musical instrument.",
                    "option4": "A specific type of Roman bread.",
                    "solution": "1"
                },
                {
                    "text": "The word 'candidate' has a direct link to ancient Roman politics. What did 'candidatus' originally mean?",
                    "hint": "It relates to the clothing worn by those seeking public office.",
                    "option1": "A person of noble birth.",
                    "option2": "A skilled orator.",
                    "option3": "A person dressed in white robes.",
                    "option4": "A military strategist.",
                    "solution": "2"
                },
                {
                    "text": "The word 'disaster' comes from the Latin 'dis astrum'. What did 'dis astrum' literally translate to?",
                    "hint": "It describes a celestial event with negative consequences.",
                    "option1": "A constellation of great fortune.",
                    "option2": "A period of abundant rainfall.",
                    "option3": "A favorable alignment of planets.",
                    "option4": "An ill-starred planet.",
                    "solution": "4"
                },
                {
                    "text": "The word 'clue' originally meant something quite different than its current meaning. What did 'clue' signify in the 15th century?",
                    "hint": "It's related to the process of shearing sheep.",
                    "option1": "A secret message.",
                    "option2": "A small piece of wool left to identify a sheep.",
                    "option3": "A type of musical instrument.",
                    "option4": "A legal document.",
                    "solution": "2"
                },
                {
                    "text": "The word 'robot' owes its existence to a Czech playwright. What is the meaning of 'robota' in Czech?",
                    "hint": "It describes a form of compulsory labor.",
                    "option1": "A mechanical device.",
                    "option2": "A type of dance.",
                    "option3": "Forced labor or servitude.",
                    "option4": "A precious gemstone.",
                    "solution": "3"
                },
                {
                    "text": "The word 'shampoo' has a fascinating journey across languages. From which Indian word does it originate?",
                    "hint": "It's related to the act of massaging and cleansing.",
                    "option1": "Namaste.",
                    "option2": "Chai.",
                    "option3": "Champo.",
                    "option4": "Yoga.",
                    "solution": "4"
                },
                {
                    "text": "The word 'quarantine' has its roots in a specific historical event. What did 'quarantena' originally refer to during the Black Death?",
                    "hint": "It describes a period of isolation.",
                    "option1": "A type of medicinal herb.",
                    "option2": "A religious ceremony.",
                    "option3": "A period of 40 days of isolation.",
                    "option4": "A form of public entertainment.",
                    "solution": "3"
                }
            ]
        },
        {
            "name": "Seminal Seeds: Unearthing Word Histories",
            "description": "Delve into the fascinating origins of words, exploring their journeys through time and across cultures. This quiz challenges your knowledge of etymology, tracing the surprising roots of common terms. Prepare to uncover the unexpected stories behind the language we use every day!",
            "questions": [
                {
                    "text": "The word 'salary' originates from the Latin word 'salarium.' What did 'salarium' originally refer to?",
                    "hint": "Think about what Roman soldiers were sometimes paid.",
                    "option1": "A type of Roman coin",
                    "option2": "A measure of grain",
                    "option3": "A ceremonial oath",
                    "option4": "An allowance of salt",
                    "solution": "1"
                },
                {
                    "text": "The word 'muscle' derives from a Latin term describing small mice. Why was this association made?",
                    "hint": "Consider the appearance of a flexed muscle.",
                    "option1": "They were believed to be a source of strength",
                    "option2": "They were considered sacred animals",
                    "option3": "They were used in ancient Roman medicine",
                    "option4": "The appearance of a flexed muscle resembled a little mouse",
                    "solution": "4"
                },
                {
                    "text": "The word 'disaster' initially had a very different meaning. What did it originally signify in ancient Greece?",
                    "hint": "It's related to celestial events.",
                    "option1": "A sudden flood",
                    "option2": "A political upheaval",
                    "option3": "An unfavorable astrological alignment",
                    "option4": "A devastating earthquake",
                    "solution": "3"
                },
                {
                    "text": "The word 'clue' comes from the Greek word 'klew,' meaning 'a branch of a tree.' How did this meaning evolve to its current usage?",
                    "hint": "Think about how people used branches to mark trails.",
                    "option1": "It referred to a type of ancient writing material",
                    "option2": "It was a term for a sacred grove",
                    "option3": "It denoted a type of musical instrument",
                    "option4": "Branches were used to mark trails, providing a guide or indication.",
                    "solution": "2"
                },
                {
                    "text": "The word 'robot' was coined by Karel Capek, a Czech writer. From what Slavic word did Capek derive the term?",
                    "hint": "It relates to forced labor.",
                    "option1": "Robota",
                    "option2": "Sloboda",
                    "option3": "Zemlja",
                    "option4": "Voda",
                    "solution": "1"
                },
                {
                    "text": "The word 'calculate' is derived from the Latin word 'calculus.' What did 'calculus' originally refer to?",
                    "hint": "It's a small, round object used for counting.",
                    "option1": "A type of Roman numeral",
                    "option2": "A unit of measurement",
                    "option3": "A small pebble or stone used for counting",
                    "option4": "A form of ancient currency",
                    "solution": "3"
                },
                {
                    "text": "The word 'quarantine' has its roots in the Venetian Republic's response to the Black Death. What does 'quaranta' mean in Italian?",
                    "hint": "It's a number.",
                    "option1": "One hundred",
                    "option2": "Fifty",
                    "option3": "Forty",
                    "option4": "Thirty",
                    "solution": "1"
                },
                {
                    "text": "The word 'avatar' originates from Sanskrit. What did the term originally signify in Hinduism?",
                    "hint": "It's a manifestation or embodiment.",
                    "option1": "A type of sacred dance",
                    "option2": "A form of ancient weaponry",
                    "option3": "The descent of a deity or revered person into a physical form",
                    "option4": "A specific type of temple architecture",
                    "solution": "4"
                }
            ]
        },
        {
            "name": "Vestiges of Voice: A Linguistic Archaeology",
            "description": "Delve into the fascinating history of words! This quiz explores the surprising origins and transformations of common terms, revealing how language evolves over time and across cultures. Prepare to unearth the hidden stories behind the words we use every day. Let's see how much you know about the roots of language!",
            "questions": [
                {
                    "text": "The word 'salary' originates from a rather unusual source. From which Roman practice does it derive?",
                    "hint": "Think about how Roman soldiers were compensated.",
                    "option1": "A system of bartering goods and services.",
                    "option2": "A lottery system for land distribution.",
                    "option3": "Payment in salt (salarium).",
                    "option4": "A tax levied on merchants.",
                    "solution": "3"
                },
                {
                    "text": "The word 'muscle' has a surprisingly animalistic origin. What did it originally refer to?",
                    "hint": "Consider the appearance of a small animal.",
                    "option1": "A type of Roman armor.",
                    "option2": "A musical instrument played during festivals.",
                    "option3": "A little mouse.",
                    "option4": "A specific type of pottery.",
                    "solution": "1"
                },
                {
                    "text": "The word 'disaster' comes from the Italian 'disastro'. What did this originally mean in a cosmological context?",
                    "hint": "It relates to astrological events.",
                    "option1": "A period of great prosperity.",
                    "option2": "A celestial alignment of planets.",
                    "option3": "An unfavorable alignment of stars.",
                    "option4": "A new constellation appearing in the sky.",
                    "solution": "3"
                },
                {
                    "text": "The word 'clue' has a fascinating journey from its original meaning. What did 'clue' originally signify in a hunting context?",
                    "hint": "It's related to the way animals are tracked.",
                    "option1": "A type of hunting dog.",
                    "option2": "A specific hunting technique.",
                    "option3": "A ball of yarn used to track game.",
                    "option4": "A signal horn used to call hunters.",
                    "solution": "1"
                },
                {
                    "text": "The word 'calculate' has roots in Latin. What did the Latin word 'calculus' originally refer to?",
                    "hint": "Think about what you might use to count with.",
                    "option1": "A type of Roman coin.",
                    "option2": "A form of ancient poetry.",
                    "option3": "Small pebbles used for counting.",
                    "option4": "A system of irrigation canals.",
                    "solution": "2"
                },
                {
                    "text": "The word 'robot' is relatively modern, but its origin is quite interesting. From which language and word does it derive?",
                    "hint": "It's connected to forced labor.",
                    "option1": "Greek, meaning 'mechanical being'.",
                    "option2": "German, meaning 'automated worker'.",
                    "option3": "Czech, meaning 'forced labor'.",
                    "option4": "Latin, meaning 'artificial life'.",
                    "solution": "3"
                },
                {
                    "text": "The word 'candidate' has a unique connection to ancient Rome. What did 'candidatus' originally mean in a political context?",
                    "hint": "It relates to the appearance of a political hopeful.",
                    "option1": "A person who campaigned secretly.",
                    "option2": "A person who held a high-ranking military position.",
                    "option3": "A person who wore white robes.",
                    "option4": "A person who was born into a noble family.",
                    "solution": "1"
                },
                {
                    "text": "The word 'shampoo' has a surprising journey across cultures. From which language and practice does it originate?",
                    "hint": "Consider traditional methods of hair washing.",
                    "option1": "French, referring to a type of hair dye.",
                    "option2": "Spanish, referring to a cleansing ritual.",
                    "option3": "Hindi (champo), referring to a head massage.",
                    "option4": "German, referring to a type of soap.",
                    "solution": "4"
                }
            ]
        },
        {
            "name": "Phonetic Footprints: A Word Origin Detective Story",
            "description": "Delve into the fascinating histories of words! This quiz explores the surprising origins and transformations of common terms, revealing how language evolves over time and across cultures. Prepare to uncover the unexpected journeys behind the words we use every day. Let's trace those phonetic footprints!",
            "questions": [
                {
                    "text": "The word 'salary' originates from a surprising source. What Roman practice is it directly linked to?",
                    "hint": "Think about ancient Roman soldiers and their payments.",
                    "option1": "The Roman Senate's annual budget allocation.",
                    "option2": "The price of grain distributed to citizens.",
                    "option3": "The cost of building Roman roads.",
                    "option4": "The allowance given to Roman soldiers, originally paid in salt.",
                    "solution": "4"
                },
                {
                    "text": "The word 'muscle' has a rather interesting etymological connection. From which Greek word does it ultimately derive?",
                    "hint": "Consider the physical appearance of a muscle and what it might resemble.",
                    "option1": "Myos, meaning 'mouse'.",
                    "option2": "Kratos, meaning 'strength'.",
                    "option3": "Demos, meaning 'people'.",
                    "option4": "Theos, meaning 'god'.",
                    "solution": "1"
                },
                {
                    "text": "The word 'disaster' originally had a very specific meaning. What was the initial meaning of 'disaster' in ancient Greek?",
                    "hint": "It relates to astrological events and their perceived influence.",
                    "option1": "A sudden and unexpected victory.",
                    "option2": "A period of great prosperity.",
                    "option3": "An ill-starred event; an unfavorable conjunction of planets.",
                    "option4": "A formal declaration of war.",
                    "solution": "3"
                },
                {
                    "text": "The word 'clue' has a fascinating journey. What did 'clue' originally mean in its early usage, before it came to mean a hint or indication?",
                    "hint": "It's related to the way animals behave.",
                    "option1": "A type of musical instrument.",
                    "option2": "A formal agreement or contract.",
                    "option3": "A ball of yarn or thread, often used by hounds.",
                    "option4": "A specific type of gemstone.",
                    "solution": "1"
                },
                {
                    "text": "The word 'robot' is relatively modern, but its origin is quite old. From which language and word does 'robot' originate, and what does it mean?",
                    "hint": "Think about theatrical performances and forced labor.",
                    "option1": "German: 'Robel', meaning 'small house'.",
                    "option2": "Latin: 'Laborare', meaning 'to work'.",
                    "option3": "Czech: 'Robota', meaning 'forced labor' or 'drudgery'.",
                    "option4": "Greek: 'Automatos', meaning 'self-moving'.",
                    "solution": "3"
                },
                {
                    "text": "The word 'calculate' has a surprising connection to pebbles. What ancient tool did it originally refer to?",
                    "hint": "Think about early forms of arithmetic.",
                    "option1": "An abacus.",
                    "option2": "A slide rule.",
                    "option3": "A counting board with pebbles.",
                    "option4": "A type of early calculator.",
                    "solution": "1"
                },
                {
                    "text": "The word 'candidate' has a direct link to ancient Roman politics. What did 'candidate' originally mean in Roman times?",
                    "hint": "It relates to someone seeking public office.",
                    "option1": "A military general.",
                    "option2": "A wealthy landowner.",
                    "option3": "Someone who is clothed in white, signifying their suitability for office.",
                    "option4": "A member of the Roman Senate.",
                    "solution": "2"
                },
                {
                    "text": "The word 'quarantine' has a dark and fascinating history, linked to a devastating plague. What does 'quaranta' (the root of 'quarantine') mean in Italian?",
                    "hint": "It's a number.",
                    "option1": "One hundred.",
                    "option2": "Fifty.",
                    "option3": "Forty.",
                    "option4": "Thirty.",
                    "solution": "3"
                }
            ]
        },
        {
            "name": "Lingua Fracta: Reconstructing Lost Tongues",
            "description": "Delve into the fascinating world of etymology and uncover the surprising origins of everyday words. This quiz explores the historical shifts, cultural influences, and linguistic migrations that have shaped the vocabulary we use today. Prepare to have your understanding of language challenged and expanded!",
            "questions": [
                {
                    "text": "The word 'salary' has a surprisingly direct connection to ancient Rome. From which Latin word does 'salary' ultimately derive, referring to a soldier's payment?",
                    "hint": "Think about how Roman soldiers were often paid.",
                    "option1": "Solarium (related to the sun)",
                    "option2": "Mercans (related to trade)",
                    "option3": "Salarium (related to salt)",
                    "option4": "Legatus (related to a commander)",
                    "solution": "1"
                },
                {
                    "text": "The word 'disaster' originally had a very specific meaning related to astrological events. What was the original meaning of 'disaster' in ancient Greek?",
                    "hint": "It's related to unfavorable celestial alignments.",
                    "option1": "A sudden storm",
                    "option2": "A period of prosperity",
                    "option3": "An ill-starred conjunction",
                    "option4": "A royal decree",
                    "solution": "3"
                },
                {
                    "text": "The English word 'muscle' has a rather amusing origin. What did the Romans originally use the word 'musculus' to describe, leading to the modern meaning?",
                    "hint": "It's a comparison to a body part.",
                    "option1": "A type of Roman armor",
                    "option2": "A musical instrument",
                    "option3": "A little mouse",
                    "option4": "A form of currency",
                    "solution": "1"
                },
                {
                    "text": "The word 'candidate' has its roots in ancient Roman politics. What did it originally signify when referring to a person seeking public office?",
                    "hint": "It's related to a specific type of garment.",
                    "option1": "A skilled orator",
                    "option2": "One who held a high-ranking position",
                    "option3": "One who was weighed",
                    "option4": "A popular general",
                    "solution": "2"
                },
                {
                    "text": "The word 'robot' is a relatively recent addition to the English language, but its origin is quite old. From which language does the word 'robot' originate, and what does it mean?",
                    "hint": "Think about Czech literature and industrial labor.",
                    "option1": "German, meaning 'mechanical being'",
                    "option2": "Latin, meaning 'artificial life'",
                    "option3": "Czech, meaning 'forced labor'",
                    "option4": "Greek, meaning 'automatism'",
                    "solution": "1"
                },
                {
                    "text": "The word 'clue' has a fascinating journey from a gambling term to its current meaning. What did 'clue' originally signify in 16th-century English, related to dice games?",
                    "hint": "It's about marking something to identify it.",
                    "option1": "A winning roll",
                    "option2": "A type of dice",
                    "option3": "A mark or spot on dice to identify them",
                    "option4": "A player's strategy",
                    "solution": "4"
                },
                {
                    "text": "The word 'quarantine' has a direct link to a historical response to disease. From what Venetian dialect does the word 'quarantena' originate, and what does it signify?",
                    "hint": "It's related to a period of isolation.",
                    "option1": "A type of medicinal herb",
                    "option2": "Forty days",
                    "option3": "A religious festival",
                    "option4": "A form of currency",
                    "solution": "2"
                },
                {
                    "text": "The word 'algebra' has a rich history, tracing back to ancient mathematics. What is the Arabic origin of the word 'algebra', and what does it originally mean?",
                    "hint": "It's related to restoring or completing something.",
                    "option1": "A type of geometric shape",
                    "option2": "The study of numbers",
                    "option3": "The reunion of broken parts",
                    "option4": "A mathematical equation",
                    "solution": "3"
                },
                {
                    "text": "The word 'knight' has evolved significantly from its earliest meaning. What was the original Germanic root of 'knight', and what did it signify?",
                    "hint": "It's related to military service and loyalty.",
                    "option1": "A type of armor",
                    "option2": "A royal title",
                    "option3": "A boy or servant",
                    "option4": "A form of transportation",
                    "solution": "1"
                },
                {
                    "text": "The word 'palindrome' is a fun linguistic concept. What does the Greek root of 'palindrome' literally mean, describing its characteristic property?",
                    "hint": "Think about how the word reads the same forwards and backwards.",
                    "option1": "A beautiful sound",
                    "option2": "A complex structure",
                    "option3": "Running back again",
                    "option4": "A hidden meaning",
                    "solution": "3"
                }
            ]
        },
        {
            "name": "Whispers of the Lexicon: A Word's Tale",
            "description": "Delve into the fascinating histories of words, uncovering their surprising origins and transformations across time and cultures. This quiz explores etymological pathways, revealing how language evolves and reflects human history. Prepare to be amazed by the unexpected journeys of everyday words!",
            "questions": [
                {
                    "text": "The word 'salary' originates from a rather unusual source. From which Roman practice does it derive?",
                    "hint": "Think about how Roman soldiers were compensated.",
                    "option1": "The payment of gladiators' fees.",
                    "option2": "The distribution of grain rations to citizens.",
                    "option3": "The disbursement of salt rations to soldiers.",
                    "option4": "The payment of taxes to the emperor.",
                    "solution": "1"
                },
                {
                    "text": "The word 'muscle' has a surprisingly animalistic origin. What did the Romans initially use the word for?",
                    "hint": "Consider the appearance of a bicep.",
                    "option1": "A type of Roman armor.",
                    "option2": "A little mouse.",
                    "option3": "A type of Roman chariot.",
                    "option4": "A specific style of Roman sandal.",
                    "solution": "2"
                },
                {
                    "text": "The word 'disaster' initially carried a very specific meaning related to astrology. What did it originally signify?",
                    "hint": "It's connected to the alignment of celestial bodies.",
                    "option1": "A favorable astrological alignment.",
                    "option2": "A period of great prosperity.",
                    "option3": "An unfavorable astrological alignment.",
                    "option4": "A royal decree.",
                    "solution": "1"
                },
                {
                    "text": "The word 'robot' is relatively modern, but its origin is quite old. From which language and word does it ultimately derive?",
                    "hint": "Think about forced labor and servitude.",
                    "option1": "Ancient Greek, meaning 'automaton'.",
                    "option2": "Czech, meaning 'forced labor'.",
                    "option3": "Latin, meaning 'artificial being'.",
                    "option4": "Sanskrit, meaning 'mechanical servant'.",
                    "solution": "3"
                },
                {
                    "text": "The word 'clue' originally meant something quite different than its current meaning. What did 'clue' signify in its earliest usage?",
                    "hint": "It's related to the way animals are managed.",
                    "option1": "A secret message.",
                    "option2": "A ball of yarn used to lead hounds.",
                    "option3": "A type of Roman coin.",
                    "option4": "A legal document.",
                    "solution": "2"
                },
                {
                    "text": "The word 'calculate' has a fascinating connection to pebbles and counting. From which language and practice does its origin stem?",
                    "hint": "Think about ancient methods of arithmetic.",
                    "option1": "Ancient Egyptian, using hieroglyphs.",
                    "option2": "Latin, from the word 'calculus' meaning 'pebbles'.",
                    "option3": "Sumerian, using clay tablets.",
                    "option4": "Greek, using an abacus.",
                    "solution": "3"
                },
                {
                    "text": "The word 'quarantine' has a direct link to a devastating historical event. What was the original purpose of the term, related to the Black Death?",
                    "hint": "It's a period of isolation.",
                    "option1": "To celebrate a victory over the plague.",
                    "option2": "To isolate ships arriving in Venice for 40 days.",
                    "option3": "To offer prayers for the sick.",
                    "option4": "To distribute medical supplies.",
                    "solution": "1"
                },
                {
                    "text": "The word 'candidate' has a surprisingly political and religious origin. What did it originally refer to in ancient Rome?",
                    "hint": "It's connected to a specific type of garment.",
                    "option1": "A Roman senator.",
                    "option2": "A person wearing a white toga, eligible for office.",
                    "option3": "A military general.",
                    "option4": "A member of the Roman priesthood.",
                    "solution": "2"
                }
            ]
        }
    ]
}